XER_Technologies_metadata_extractor/__init__.py
XER_Technologies_metadata_extractor/extract.py
XER_Technologies_metadata_extractor/file_config.py
XER_Technologies_metadata_extractor/metadata_calculator.py
XER_Technologies_metadata_extractor/metadata_config.py
XER_Technologies_metadata_extractor/postprocessing_integration.py
XER_Technologies_metadata_extractor/utilities.py
XER_Technologies_metadata_extractor/validation.py
XER_Technologies_metadata_extractor/validation_config.py
XER_Technologies_metadata_extractor/postprocessing/__init__.py
XER_Technologies_metadata_extractor/postprocessing/calculation_functions.py
XER_Technologies_metadata_extractor/postprocessing/naming_functions.py
XER_Technologies_metadata_extractor/postprocessing/validation_analysis.py
XER_Technologies_metadata_extractor/reference_data/RPM_power_30_throttle.csv
XER_Technologies_metadata_extractor/reference_data/RPM_power_40_throttle.csv
XER_Technologies_metadata_extractor/reference_data/RPM_power_50_throttle.csv
XER_Technologies_metadata_extractor/reference_data/RPM_power_60_throttle.csv
XER_Technologies_metadata_extractor/reference_data/RPM_power_70_throttle.csv
XER_Technologies_metadata_extractor/reference_data/RPM_power_80_throttle.csv
XER_Technologies_metadata_extractor/reference_data/RPM_power_90_throttle.csv
XER_Technologies_metadata_extractor/reference_data/RPM_power_99_throttle.csv
xer_technologies_metadata_extractor-0.6.1.dist-info/METADATA
xer_technologies_metadata_extractor-0.6.1.dist-info/WHEEL
xer_technologies_metadata_extractor-0.6.1.dist-info/top_level.txt
xer_technologies_metadata_extractor-0.6.1.dist-info/RECORD
