Metadata-Version: 2.4
Name: XER_Technologies_metadata_extractor
Version: 0.6.1
Summary: Internal data extraction utilities
Author-email: Jakob Wiren <jakob.wiren@xer-tech.com>
Classifier: Development Status :: 3 - Alpha
Classifier: Intended Audience :: Developers
Classifier: Programming Language :: Python :: 3
Classifier: Programming Language :: Python :: 3.8
Classifier: Programming Language :: Python :: 3.9
Classifier: Programming Language :: Python :: 3.10
Classifier: Programming Language :: Python :: 3.11
Requires-Python: >=3.8
Requires-Dist: pandas>=2.0.0
Requires-Dist: scipy>=1.11.0
Requires-Dist: boto3>=1.34.0
Provides-Extra: dev
Requires-Dist: pytest>=7.0.0; extra == "dev"
Requires-Dist: pytest-cov>=4.0.0; extra == "dev"
Requires-Dist: black>=23.0.0; extra == "dev"
Requires-Dist: isort>=5.0.0; extra == "dev"
Requires-Dist: mypy>=1.0.0; extra == "dev"
Requires-Dist: ruff>=0.0.290; extra == "dev"
Requires-Dist: types-boto3>=1.0.2; extra == "dev"
